filter_variants/__init__.py
filter_variants/log.py
filter_variants/cli/__init__.py
filter_variants/cli/root.py
filter_variants/utils/__init__.py
filter_variants/utils/get_tabix_handle.py
filter_variants/utils/read_tabix_files.py
filter_variants/utils/tabix_tools.py
filter_variants/warnings/__init__.py
filter_variants/warnings/exceptions.py
filter_variants-0.3.dist-info/DESCRIPTION.rst
filter_variants-0.3.dist-info/entry_points.txt
filter_variants-0.3.dist-info/METADATA
filter_variants-0.3.dist-info/metadata.json
filter_variants-0.3.dist-info/RECORD
filter_variants-0.3.dist-info/top_level.txt
filter_variants-0.3.dist-info/WHEEL
