Metadata-Version: 2.0
Name: filter-variants
Version: 0.3
Summary: Filter variants based on frequencies
Home-page: https://github.com/moonso/filter_variants
Author: Måns Magnusson
Author-email: mans.magnusson@scilifelab.se
License: MIT
Keywords: sequencing exome genome
Platform: UNKNOWN
Classifier: Development Status :: 3 - Alpha
Classifier: Intended Audience :: Science/Research
Classifier: Topic :: Software Development
Classifier: Topic :: Scientific/Engineering :: Bio-Informatics
Classifier: License :: OSI Approved :: MIT License
Classifier: Programming Language :: Python :: 2
Classifier: Programming Language :: Python :: 2.7
Classifier: Programming Language :: Python :: 3
Classifier: Programming Language :: Python :: 3.3
Classifier: Programming Language :: Python :: 3.4
Classifier: Environment :: Console
Requires-Dist: click
Requires-Dist: setuptools
Requires-Dist: pytabix
Requires-Dist: vcftoolbox
Requires-Dist: extract-vcf
